README.md
conftest.py
constraints.in
requirements.txt
setup.cfg
setup.py
tldeploy/__init__.py
tldeploy/cli.py
tldeploy/core.py
tldeploy/exchange.py
tldeploy/identity-proxy.json
tldeploy/identity.py
tldeploy/interests.py
tldeploy/load_contracts.py
tldeploy/migration.py
tldeploy/signing.py
trustlines_contracts_deploy.egg-info/PKG-INFO
trustlines_contracts_deploy.egg-info/SOURCES.txt
trustlines_contracts_deploy.egg-info/dependency_links.txt
trustlines_contracts_deploy.egg-info/entry_points.txt
trustlines_contracts_deploy.egg-info/requires.txt
trustlines_contracts_deploy.egg-info/top_level.txt