Metadata-Version: 2.1
Name: trustlines-contracts-deploy
Version: 1.3.0
Summary: deploy trustlines contracts
Home-page: https://github.com/trustlines-protocol/contracts
Author: Trustlines-Network
Author-email: contact@brainbot.com
License: MIT
Keywords: trustlines
Platform: UNKNOWN
Classifier: Development Status :: 2 - Pre-Alpha
Classifier: Intended Audience :: Developers
Classifier: License :: OSI Approved :: MIT License
Classifier: Programming Language :: Python :: 3
Classifier: Programming Language :: Python :: 3.5
Classifier: Programming Language :: Python :: 3.6
Requires-Python: >=3.6
